{"id":"lA7u","imageCount":16,"latitude":1.28645,"longitude":103.84468,"name":"Furama City Centre","address":"60 Eu Tong Sen Street","address1":"60 Eu Tong Sen Street","rating":4.0,"trustyou":{"id":"4489634b-e626-44ea-b038-8733d98b377a","score":{"overall":80.0,"kaligo_overall":4.0,"solo":75.0,"couple":76.0,"family":75.0,"business":71.0}},"categories":{"overall":{"name":"Overall","score":74,"popularity":61.0},"city_hotel":{"name":"City Hotel","score":73,"popularity":18.21749130434782},"business_hotel":{"name":"Business Hotel","score":82,"popularity":31.1305347826087}},"amenities_ratings":[{"name":"Location","score":97},{"name":"Food","score":86},{"name":"Service","score":84},{"name":"Room","score":72},{"name":"Vibe","score":65},{"name":"Comfort","score":62},{"name":"Amenities","score":47},{"name":"Pool","score":38},{"name":"Wellness","score":33},{"name":"WiFi","score":31}],"description":"<p><b>Property Location</b> <br />With a stay at Furama City Centre in Singapore (Financial District Singapore), you'll be minutes from Hong Lim Food Centre and Chinatown Heritage Center.  This 4-star hotel is close to <b>Universal Studios Singapore</b>® and National Orchid Garden.</p><p><b>Rooms</b> <br />Make yourself at home in one of the 445 air-conditioned rooms featuring minibars. Satellite television is provided for your entertainment. Bathrooms have complimentary toiletries and hair dryers. Conveniences include phones, as well as safes and desks.</p><p><b>Amenities</b> <br />Take advantage of recreation opportunities including an outdoor pool and a fitness center. Additional features include complimentary wireless Internet access, concierge services, and babysitting/childcare (surcharge).</p><p><b>Dining</b> <br />Enjoy a meal at a restaurant or in a coffee shop/café. Or stay in and take advantage of the hotel's 24-hour room service.</p><p><b>Business, Other Amenities</b> <br />Featured amenities include limo/town car service, express check-in, and dry cleaning/laundry services. Event facilities at this hotel consist of conference space and meeting rooms. Free self parking is available onsite.</p>","amenities":{"airConditioning":true,"businessCenter":true,"clothingIron":true,"dryCleaning":true,"hairDryer":true,"meetingRooms":true,"miniBarInRoom":true,"outdoorPool":true,"parkingGarage":true,"roomService":true,"safe":true,"tVInRoom":true,"voiceMail":true},"original_metadata":{"name":null,"city":"Singapore","state":null,"country":"SG"},"image_details":{"suffix":".jpg","count":16,"prefix":"https://d2ey9sqrvkqdfs.cloudfront.net/lA7u/"},"hires_image_index":"0,1,2,3,4,5,6,7,8,9,10,11,12,13,14,15","number_of_images":75,"default_image_index":1,"imgix_url":"https://kaligo-web-expedia.imgix.net","cloudflare_image_url":"https://www.kaligo-staging.xyz/images/new"}